fat_wheel/__init__.py
fat_wheel/arg_process.py
fat_wheel/cli.py
fat_wheel/fat.py
fat_wheel/fs.py
fat_wheel/gen.py
fat_wheel/project_model.py
fat_wheel/template_writer.py
fat_wheel/utils.py
fat_wheel/cmd/__init__.py
fat_wheel/cmd/pip.py
fat_wheel/parse/__init__.py
fat_wheel/parse/config.py
fat_wheel/parse/py_file.py
fat_wheel/parse/yaml.py
fat_wheel/template/runner.py
fat_wheel/template/setup.txt
fat_wheel-1.5.5b0.dist-info/LICENSE
fat_wheel-1.5.5b0.dist-info/METADATA
fat_wheel-1.5.5b0.dist-info/WHEEL
fat_wheel-1.5.5b0.dist-info/entry_points.txt
fat_wheel-1.5.5b0.dist-info/top_level.txt
fat_wheel-1.5.5b0.dist-info/RECORD
