Metadata-Version: 2.1
Name: fat-wheel
Version: 1.5.5b0
Summary: generate fat wheel similar to fat jar in java
Author: Abhinav Jain
Author-email: ajchirawa@gmail.com
License: MIT
License-File: LICENSE
Requires-Dist: Jinja2 (==3.1.2)
Requires-Dist: MarkupSafe (==2.1.1)
Requires-Dist: pkginfo (==1.8.3)
Requires-Dist: PyYAML (==6.0)
Requires-Dist: wheel
